beastling/__init__.py
beastling/__main__.py
beastling/beast_maps.py
beastling/beastxml.py
beastling/cli.py
beastling/configuration.py
beastling/distributions.py
beastling/extractor.py
beastling/report.py
beastling/clocks/__init__.py
beastling/clocks/baseclock.py
beastling/clocks/prior.py
beastling/clocks/random.py
beastling/clocks/relaxed.py
beastling/clocks/strict.py
beastling/data/glottolog-2.7-geo.csv
beastling/data/glottolog-2.7.newick
beastling/data/glottolog-3.0-geo.csv
beastling/data/glottolog-3.0.newick
beastling/data/glottolog-4.0-geo.csv
beastling/data/glottolog-4.0.newick
beastling/fileio/__init__.py
beastling/fileio/datareaders.py
beastling/models/__init__.py
beastling/models/basemodel.py
beastling/models/binary.py
beastling/models/binaryctmc.py
beastling/models/bsvs.py
beastling/models/covarion.py
beastling/models/dollo.py
beastling/models/geo.py
beastling/models/mk.py
beastling/models/pseudodollo.py
beastling/models/pseudodollocovarion.py
beastling/treepriors/__init__.py
beastling/treepriors/base.py
beastling/treepriors/coalescent.py
beastling-1.5.1.dist-info/LICENSE
beastling-1.5.1.dist-info/METADATA
beastling-1.5.1.dist-info/WHEEL
beastling-1.5.1.dist-info/entry_points.txt
beastling-1.5.1.dist-info/top_level.txt
beastling-1.5.1.dist-info/RECORD
