Metadata-Version: 2.1
Name: beastling
Version: 1.5.1
Summary: Command line tool to help mortal linguists use BEAST
Home-page: UNKNOWN
Author: Luke Maurits
Author-email: luke@maurits.id.au
License: BSD (3 clause)
Platform: UNKNOWN
Classifier: Programming Language :: Python
Classifier: Programming Language :: Python :: 3
Classifier: Programming Language :: Python :: 3.4
Classifier: Programming Language :: Python :: 3.5
Classifier: License :: OSI Approved :: BSD License
Requires-Dist: six
Requires-Dist: newick (>=0.6.0)
Requires-Dist: appdirs
Requires-Dist: clldutils (~=2.0)
Requires-Dist: pycldf
